cbcdb/__init__.py
cbcdb/__inti__.py
cbcdb/configuration_service.py
cbcdb/main.py
cbcdb/test.py
tests/__init__.py
tests/test_db_manager.py
cbcdb-1.0.3.dist-info/LICENSE
cbcdb-1.0.3.dist-info/METADATA
cbcdb-1.0.3.dist-info/WHEEL
cbcdb-1.0.3.dist-info/top_level.txt
cbcdb-1.0.3.dist-info/RECORD
