Metadata-Version: 2.1
Name: cbcdb
Version: 1.0.3
Summary: A package to help facilitate postgres and Redshift database communication over SSH.
Home-page: https://github.com/Cold-Bore-Capital/cbc-dbmanager
Author: Cold Bore Capital
Author-email: it-group@coldborecapital.com
License: UNKNOWN
Platform: UNKNOWN
Classifier: Programming Language :: Python :: 3.8
Classifier: Topic :: Software Development :: Libraries :: Python Modules
Classifier: Development Status :: 5 - Production/Stable
Requires-Python: >=3.7.1
Requires-Dist: psycopg2-binary (>=2.8)
Requires-Dist: sshtunnel (>=0.4.0)
Requires-Dist: pandas (>=1.2)
